Metadata-Version: 2.4
Name: garch-calculator
Version: 2.0.0
Summary: High-Performance GARCH Calculator with Incremental Updates and Preset Parameters
Home-page: https://github.com/biteasquirrel/garch-calculator
Author: biteasquirrel
Author-email: biteasquirrel <biteasquirrel@gmail.com>
Maintainer-email: biteasquirrel <biteasquirrel@gmail.com>
License: MIT
Project-URL: Homepage, https://github.com/biteasquirrel/garch-calculator
Project-URL: Bug Reports, https://github.com/biteasquirrel/garch-calculator/issues
Project-URL: Source, https://github.com/biteasquirrel/garch-calculator
Project-URL: Documentation, https://github.com/biteasquirrel/garch-calculator/blob/main/README.md
Project-URL: Repository, https://github.com/biteasquirrel/garch-calculator.git
Keywords: garch,volatility,finance,econometrics,time-series,forecasting,risk-management,financial-modeling
Classifier: Development Status :: 5 - Production/Stable
Classifier: Intended Audience :: Financial and Insurance Industry
Classifier: Intended Audience :: Science/Research
Classifier: Intended Audience :: Developers
Classifier: License :: OSI Approved :: MIT License
Classifier: Operating System :: POSIX :: Linux
Classifier: Operating System :: MacOS :: MacOS X
Classifier: Operating System :: Microsoft :: Windows
Classifier: Programming Language :: C++
Classifier: Programming Language :: Python :: 3
Classifier: Programming Language :: Python :: 3.7
Classifier: Programming Language :: Python :: 3.8
Classifier: Programming Language :: Python :: 3.9
Classifier: Programming Language :: Python :: 3.10
Classifier: Programming Language :: Python :: 3.11
Classifier: Programming Language :: Python :: 3.12
Classifier: Topic :: Office/Business :: Financial
Classifier: Topic :: Scientific/Engineering :: Mathematics
Classifier: Topic :: Scientific/Engineering :: Information Analysis
Classifier: Topic :: Software Development :: Libraries :: Python Modules
Requires-Python: >=3.7
License-File: LICENSE
Requires-Dist: numpy>=1.18.0
Provides-Extra: test
Requires-Dist: pytest>=6.0; extra == "test"
Requires-Dist: pytest-cov; extra == "test"
Requires-Dist: numpy; extra == "test"
Provides-Extra: dev
Requires-Dist: pytest>=6.0; extra == "dev"
Requires-Dist: pytest-cov; extra == "dev"
Requires-Dist: black; extra == "dev"
Requires-Dist: isort; extra == "dev"
Requires-Dist: flake8; extra == "dev"
Requires-Dist: mypy; extra == "dev"
Requires-Dist: build; extra == "dev"
Requires-Dist: twine; extra == "dev"
Provides-Extra: validation
Requires-Dist: yfinance>=0.1.63; extra == "validation"
Requires-Dist: pandas>=1.3.0; extra == "validation"
Requires-Dist: scikit-learn>=1.0.0; extra == "validation"
Requires-Dist: matplotlib>=3.3.0; extra == "validation"
Requires-Dist: arch>=5.0.0; extra == "validation"
Provides-Extra: all
Requires-Dist: garch-calculator[dev,test,validation]; extra == "all"
Dynamic: author
Dynamic: home-page
Dynamic: license-file
Dynamic: requires-python
